[
    {
        "index": 0,
        "input_text": "\u6cb3\u6c60\u897f\u6bb5\u8fb9\u5761\u5728\u6301\u7eed\u964d\u96e8\u540e\u51fa\u73b0\u65b0\u7684\u88c2\u7f1d\u5e26\uff0c\u5761\u9762\u788e\u843d\u7269\u660e\u663e\u589e\u591a\u3002\n\u73b0\u573a\u6392\u67e5\u53d1\u73b0\u9632\u62a4\u6784\u9020\u53d7\u635f\uff0c\u6b21\u751f\u6ed1\u584c\u98ce\u9669\u8f83\u9ad8\uff0c\u5efa\u8bae\u7acb\u523b\u5c01\u63a7\u5e76\u7ec4\u7ec7\u4e13\u5bb6\u590d\u6838\u3002",
        "entity_hint": "",
        "relation_hint": "",
        "oie": [
            [
                "\u6cb3\u6c60\u897f\u6bb5\u8fb9\u5761",
                "\u51fa\u73b0",
                "\u65b0\u7684\u88c2\u7f1d\u5e26"
            ],
            [
                "\u5761\u9762",
                "\u5b58\u5728",
                "\u788e\u843d\u7269\u589e\u591a"
            ],
            [
                "\u9632\u62a4\u6784\u9020",
                "\u72b6\u6001",
                "\u53d7\u635f"
            ],
            [
                "\u6b21\u751f\u6ed1\u584c",
                "\u98ce\u9669",
                "\u8f83\u9ad8"
            ],
            [
                "\u6cb3\u6c60\u897f\u6bb5\u8fb9\u5761",
                "\u5efa\u8bae",
                "\u7acb\u523b\u5c01\u63a7"
            ],
            [
                "\u6cb3\u6c60\u897f\u6bb5\u8fb9\u5761",
                "\u5efa\u8bae",
                "\u7ec4\u7ec7\u4e13\u5bb6\u590d\u6838"
            ]
        ],
        "schema_definition": {
            "\u51fa\u73b0": "\u4e3b\u8bed\u5b9e\u4f53\u4ea7\u751f\u3001\u663e\u73b0\u6216\u53d1\u751f\u4e86\u5bbe\u8bed\u6240\u8868\u793a\u7684\u73b0\u8c61\u3001\u7279\u5f81\u6216\u5bf9\u8c61\u3002",
            "\u5b58\u5728": "\u4e3b\u8bed\u5b9e\u4f53\u5177\u6709\u3001\u5305\u542b\u6216\u53d1\u751f\u4e86\u5bbe\u8bed\u6240\u8868\u793a\u7684\u73b0\u8c61\u3001\u72b6\u51b5\u6216\u5c5e\u6027\u3002",
            "\u72b6\u6001": "\u5bbe\u8bed\u63cf\u8ff0\u4e3b\u8bed\u5b9e\u4f53\u5f53\u524d\u7684\u72b6\u51b5\u3001\u5de5\u51b5\u6216\u5c5e\u6027\u7279\u5f81\u3002",
            "\u98ce\u9669": "\u5bbe\u8bed\u63cf\u8ff0\u4e3b\u8bed\u5b9e\u4f53\u6240\u9762\u4e34\u7684\u98ce\u9669\u7a0b\u5ea6\u3001\u7b49\u7ea7\u6216\u53d1\u751f\u53ef\u80fd\u6027\u3002",
            "\u5efa\u8bae": "\u9488\u5bf9\u4e3b\u8bed\u5b9e\u4f53\uff0c\u63d0\u51fa\u6216\u63a8\u8350\u91c7\u53d6\u5bbe\u8bed\u6240\u8868\u793a\u7684\u5904\u7f6e\u63aa\u65bd\u6216\u884c\u52a8\u65b9\u6848\u3002"
        },
        "canonicalization_candidates": "[{'contains administrative territorial entity': np.float32(0.5284982), 'start time': np.float32(0.51683384), 'located in the administrative territorial entity': np.float32(0.5067172), 'contains settlement': np.float32(0.4812683), 'date of birth': np.float32(0.47711083)}, {'\u51fa\u73b0': np.float32(0.8954396), 'contains administrative territorial entity': np.float32(0.57021296), 'located in the administrative territorial entity': np.float32(0.523196), 'start time': np.float32(0.50439346), 'contains settlement': np.float32(0.47082487)}, {'\u51fa\u73b0': np.float32(0.7595921), 'contains administrative territorial entity': np.float32(0.44165167), 'located in the administrative territorial entity': np.float32(0.43389016), 'start time': np.float32(0.4261942), 'contains settlement': np.float32(0.40506017)}, {'\u72b6\u6001': np.float32(0.8517447), '\u51fa\u73b0': np.float32(0.6793231), 'contains administrative territorial entity': np.float32(0.410273), 'start time': np.float32(0.4101187), 'located in the administrative territorial entity': np.float32(0.39635348)}, {'\u51fa\u73b0': np.float32(0.63334227), '\u72b6\u6001': np.float32(0.6281757), '\u98ce\u9669': np.float32(0.61447877), 'contains administrative territorial entity': np.float32(0.44998288), 'contains settlement': np.float32(0.44199187)}, {}]",
        "schema_canonicalizaiton": [
            [
                "\u6cb3\u6c60\u897f\u6bb5\u8fb9\u5761",
                "\u51fa\u73b0",
                "\u65b0\u7684\u88c2\u7f1d\u5e26"
            ],
            [
                "\u5761\u9762",
                "\u51fa\u73b0",
                "\u788e\u843d\u7269\u589e\u591a"
            ],
            [
                "\u9632\u62a4\u6784\u9020",
                "\u72b6\u6001",
                "\u53d7\u635f"
            ],
            [
                "\u6b21\u751f\u6ed1\u584c",
                "\u98ce\u9669",
                "\u8f83\u9ad8"
            ],
            [
                "\u6cb3\u6c60\u897f\u6bb5\u8fb9\u5761",
                "\u5efa\u8bae",
                "\u7acb\u523b\u5c01\u63a7"
            ],
            [
                "\u6cb3\u6c60\u897f\u6bb5\u8fb9\u5761",
                "\u5efa\u8bae",
                "\u7ec4\u7ec7\u4e13\u5bb6\u590d\u6838"
            ]
        ]
    }
]